setup.cfg
setup.py
allegro_franz/__init__.py
allegro_franz/reader.py
allegro_franz/util.py
allegro_franz/writer.py
allegro_franz/test/__init__.py
allegro_franz/test/test_allegro.py
surf.allegro_franz.egg-info/PKG-INFO
surf.allegro_franz.egg-info/SOURCES.txt
surf.allegro_franz.egg-info/dependency_links.txt
surf.allegro_franz.egg-info/entry_points.txt
surf.allegro_franz.egg-info/requires.txt
surf.allegro_franz.egg-info/top_level.txt