Metadata-Version: 1.1
Name: surf.allegro-franz
Version: 0.2.2-r348
Summary: surf AllegroGraph plugin
Home-page: http://code.google.com/p/surfrdf/
Author: Cosmin Basca
Author-email: cosmin.basca at google.com
License: New BSD SOFTWARE
Keywords: python SPARQL RDF resource mapper
Platform: any
Classifier: Development Status :: 3 - Alpha
Classifier: Intended Audience :: Developers
Classifier: License :: OSI Approved :: BSD License
Classifier: Operating System :: OS Independent
Classifier: Programming Language :: Python :: 2.5
Requires: simplejson
